environments/__init__.py
environments/es_env.py
environments/ts_env.py
environments/scenario_configurations/es_use_case.json
environments/scenario_configurations/ts_use_case.json
nsoran/__init__.py
nsoran/action_controller.py
nsoran/datalake.py
nsoran/ns_env.py
nsoran-0.0.1.dist-info/METADATA
nsoran-0.0.1.dist-info/WHEEL
nsoran-0.0.1.dist-info/licenses/LICENSE
nsoran-0.0.1.dist-info/RECORD
