Metadata-Version: 2.4
Name: nsoran
Version: 0.0.1
Summary: Gymnasium environment for ns-O-RAN.
Project-URL: Homepage, https://openrangym.com/ran-frameworks/ns-o-ran
Project-URL: Package, https://pypi.org/project/nsoran/
Project-URL: Source, https://github.com/wineslab/ns-o-ran-gym
Project-URL: Bug Tracker, https://github.com/wineslab/ns-o-ran-gym/issues
Author-email: Andrea Lacava <thecave003@gmail.com>, Tommaso Pietrosanti <pietrosantitommaso@protonmail.com>
License-File: LICENSE
Keywords: 5g,gym,gymnasium,ns-3,ns-O-RAN,o-ran
Classifier: Development Status :: 4 - Beta
Classifier: Programming Language :: Python
Classifier: Programming Language :: Python :: 3.8
Classifier: Programming Language :: Python :: 3.9
Classifier: Programming Language :: Python :: 3.10
Classifier: Programming Language :: Python :: 3.11
Classifier: Programming Language :: Python :: 3.12
Classifier: Programming Language :: Python :: Implementation :: CPython
Classifier: Programming Language :: Python :: Implementation :: PyPy
Requires-Python: >=3.8
Requires-Dist: gymnasium==0.29.0
Requires-Dist: numpy==2.1.1
Requires-Dist: pandas==2.2.3
Requires-Dist: posix-ipc==1.1.1
Requires-Dist: sem==0.3.9.1
Requires-Dist: typing==3.7.4.3
